{
    "example_source": [
        "▁我还",
        "澄清",
        "了",
        "在该",
        "会议上",
        "提出的",
        "若干",
        "事项",
        "。"
    ],
    "example_target": [
        "<s>",
        "▁i",
        "▁was",
        "▁able",
        "▁to",
        "▁provide",
        "▁clarification",
        "▁on",
        "▁some",
        "▁of",
        "▁the",
        "▁matters",
        "▁which",
        "▁were",
        "▁raised",
        "▁at",
        "▁that",
        "▁meeting",
        ".",
        "</s>"
    ],
    "hypotheses": [
        {
            "hypothesis": [
                "▁i",
                "▁have",
                "▁also",
                "▁clarified",
                "▁a",
                "▁number",
                "▁of",
                "▁matters",
                "▁raised",
                "▁by",
                "▁the",
                "▁conference",
                "."
            ],
            "score": -6.022862911224365
        },
        {
            "hypothesis": [
                "▁i",
                "▁have",
                "▁also",
                "▁clarified",
                "▁a",
                "▁number",
                "▁of",
                "▁matters",
                "▁raised",
                "▁by",
                "▁the",
                "▁meeting",
                "."
            ],
            "score": -6.890648365020752
        },
        {
            "hypothesis": [
                "▁i",
                "▁have",
                "▁also",
                "▁clarified",
                "▁a",
                "▁number",
                "▁of",
                "▁matters",
                "▁raised",
                "▁dur",
                "ing",
                "▁the",
                "▁meeting",
                "."
            ],
            "score": -7.5567121505737305
        },
        {
            "hypothesis": [
                "▁i",
                "▁have",
                "▁also",
                "▁clarified",
                "▁a",
                "▁number",
                "▁of",
                "▁issues",
                "▁raised",
                "▁by",
                "▁the",
                "▁conference",
                "."
            ],
            "score": -7.6854119300842285
        },
        {
            "hypothesis": [
                "▁i",
                "▁have",
                "▁also",
                "▁clarified",
                "▁a",
                "▁number",
                "▁of",
                "▁matters",
                "▁raised",
                "▁by",
                "▁the",
                "▁session",
                "."
            ],
            "score": -7.763708591461182
        },
        {
            "hypothesis": [
                "▁i",
                "▁have",
                "▁clarified",
                "▁a",
                "▁number",
                "▁of",
                "▁matters",
                "▁raised",
                "▁by",
                "▁the",
                "▁conference",
                "."
            ],
            "score": -7.966619491577148
        },
        {
            "hypothesis": [
                "▁i",
                "▁clarified",
                "▁a",
                "▁number",
                "▁of",
                "▁matters",
                "▁raised",
                "▁by",
                "▁the",
                "▁conference",
                "."
            ],
            "score": -8.014853477478027
        },
        {
            "hypothesis": [
                "▁i",
                "▁have",
                "▁also",
                "▁clarified",
                "▁a",
                "▁number",
                "▁of",
                "▁questions",
                "▁raised",
                "▁by",
                "▁the",
                "▁conference",
                "."
            ],
            "score": -8.091863632202148
        },
        {
            "hypothesis": [
                "▁i",
                "▁have",
                "▁also",
                "▁clarified",
                "▁the",
                "▁number",
                "▁of",
                "▁matters",
                "▁raised",
                "▁by",
                "▁the",
                "▁conference",
                "."
            ],
            "score": -8.109786987304688
        },
        {
            "hypothesis": [
                "▁i",
                "▁have",
                "▁also",
                "▁clarified",
                "▁a",
                "▁number",
                "▁of",
                "▁matters",
                "▁raised",
                "▁dur",
                "ing",
                "▁the",
                "▁conference",
                "."
            ],
            "score": -8.168743133544922
        }
    ],
    "diagnostic_info": "eyJ0IjogIjIwMjQtMDktMDRUMDU6MzU6MjAuNjMzMzM2IiwgImgiOiAiODliNWY1N2I4N2I0IiwgInUiOiAicm9vdCJ9"
}